{
  "file": "bandwidth_budgeter.py",
  "properties": [
    {
      "scope": "function",
      "function": "bandwidth_budgeter",
      "property": "defines_function",
      "element": "bandwidth_budgeter",
      "formal": "bandwidth_budgeter(total, weights) is defined"
    },
    {
      "scope": "branch",
      "function": "bandwidth_budgeter",
      "element": "bandwidth_budgeter",
      "condition": "total < 0",
      "property": "raises_on_condition",
      "formal": "if total < 0 then raises ValueError(\"total must be non-negative\")"
    },
    {
      "scope": "branch",
      "function": "bandwidth_budgeter",
      "element": "bandwidth_budgeter",
      "condition": "minimum < 0",
      "property": "raises_on_condition",
      "formal": "if minimum < 0 then raises ValueError(\"minimum must be non-negative\")"
    },
    {
      "scope": "branch",
      "function": "bandwidth_budgeter",
      "element": "bandwidth_budgeter",
      "condition": "not weights",
      "property": "raises_on_condition",
      "formal": "if not weights then raises ValueError(\"no weights provided\")"
    },
    {
      "scope": "branch",
      "function": "bandwidth_budgeter",
      "element": "bandwidth_budgeter",
      "condition": "not any(weights)",
      "property": "raises_on_condition",
      "formal": "if not any(weights) then raises ValueError(\"all weights are zero\")"
    }
  ],
  "error": null
}
